tests/__init__.py
tests/test_views.py
udata_schema_gouvfr/__init__.py
udata_schema_gouvfr/settings.py
udata_schema_gouvfr/tasks.py
udata_schema_gouvfr/views.py
udata_schema_gouvfr/templates/button.html
udata_schema_gouvfr/templates/modal.html
udata_schema_gouvfr-1.3.2.dist-info/LICENSE
udata_schema_gouvfr-1.3.2.dist-info/METADATA
udata_schema_gouvfr-1.3.2.dist-info/WHEEL
udata_schema_gouvfr-1.3.2.dist-info/entry_points.txt
udata_schema_gouvfr-1.3.2.dist-info/top_level.txt
udata_schema_gouvfr-1.3.2.dist-info/RECORD
