Metadata-Version: 2.1
Name: udata-schema-gouvfr
Version: 1.3.2
Summary: Integration with schema.data.gouv.fr
Home-page: https://github.com/etalab/udata-schema-gouvfr
Author: Etalab
Author-email: pypi@data.gouv.fr
License: MIT
Keywords: udata,schema,tableschema
Platform: UNKNOWN
Classifier: Development Status :: 3 - Alpha
Classifier: Programming Language :: Python
Classifier: Environment :: Web Environment
Classifier: Operating System :: OS Independent
Classifier: Intended Audience :: Developers
Classifier: Topic :: System :: Software Distribution
Classifier: Programming Language :: Python
Classifier: Programming Language :: Python :: 3
Classifier: Programming Language :: Python :: 3.7
Classifier: Topic :: Software Development :: Libraries :: Python Modules
License-File: LICENSE
Requires-Dist: udata (>=2.1.4.dev)
Requires-Dist: requests
Provides-Extra: test
Requires-Dist: httpretty (==0.9.7) ; extra == 'test'
Requires-Dist: mock (==3.0.5) ; extra == 'test'
Requires-Dist: pytest-flask (==0.15.0) ; extra == 'test'
Requires-Dist: pytest-sugar (==0.9.2) ; extra == 'test'
Requires-Dist: pytest (==4.6.3) ; extra == 'test'
Requires-Dist: requests-mock ; extra == 'test'
